README.md
setup.py
PygFW/Cake.py
PygFW/Constants.py
PygFW/Engine.py
PygFW/Entity.py
PygFW/Event.py
PygFW/Scene.py
PygFW/Volatile.py
PygFW/__init__.py
PygFW.egg-info/PKG-INFO
PygFW.egg-info/SOURCES.txt
PygFW.egg-info/dependency_links.txt
PygFW.egg-info/requires.txt
PygFW.egg-info/top_level.txt
PygFW/Builtin/__init__.py
PygFW/Builtin/Entities/BackgroundEntity.py
PygFW/Builtin/Entities/ButtonEntity.py
PygFW/Builtin/Entities/ParticulateEntity.py
PygFW/Builtin/Entities/__init__.py
PygFW/Builtin/Events/EntityClickEvent.py
PygFW/Builtin/Events/QuitEvent.py
PygFW/Builtin/Events/__init__.py
PygFW/Data/DataContainer.py
PygFW/Data/Manipulator.py
PygFW/Data/__init__.py
PygFW/Image/ImageBank.py
PygFW/Image/ImageGallery.py
PygFW/Image/ImageObject.py
PygFW/Image/__init__.py
PygFW/Text/Character.py
PygFW/Text/TextField.py
PygFW/Text/__init__.py