Metadata-Version: 2.1
Name: PygFW
Version: 0.1a0
Summary: Create a simple yet effective server with and connect to it with a simple client!
Home-page: https://github.com/shauncameron/PygFW
Author: Shaun Cameron
Author-email: shauncameron13034@gmail.com
License: MIT
Platform: UNKNOWN
